README.md
setup.py
filterable/__init__.py
filterable/filterable.py
filterable.egg-info/PKG-INFO
filterable.egg-info/SOURCES.txt
filterable.egg-info/dependency_links.txt
filterable.egg-info/requires.txt
filterable.egg-info/top_level.txt
filterable/exceptions/__init__.py
filterable/exceptions/filtering_exception.py
filterable/exceptions/no_request_context_exception.py
filterable/helpers/paginate.py
filterable/request/__init__.py
filterable/request/request_handler.py
filterable/types/__init__.py
filterable/types/array.py
filterable/types/json.py