Metadata-Version: 2.1
Name: filterable
Version: 0.0.1
Summary: Filterable handler to handle with request filters
Home-page: https://github.com/totvslabs/filterable
Author: TotvsLabs
Author-email: info@totvslabs.com
Keywords: pagination,assistant,handler,helper,filter,request,args,paginate,filters,filtering
Requires-Python: >=3.7
